httpetcd/__init__.py
httpetcd/clients.py
httpetcd/constants.py
httpetcd/exceptions.py
httpetcd/version.py
httpetcd/base/__init__.py
httpetcd/base/client.py
httpetcd/base/managers.py
httpetcd/common/__init__.py
httpetcd/common/exc.py
httpetcd/common/obj.py
httpetcd/library/__init__.py
httpetcd/library/session.py
httpetcd/raw/__init__.py
httpetcd/raw/client.py
httpetcd/raw/entities/__init__.py
httpetcd/raw/entities/lease.py
httpetcd/raw/managers/__init__.py
httpetcd/raw/managers/kv.py
httpetcd/raw/managers/lease.py
httpetcd/server/__init__.py
httpetcd/server/codes.py
httpetcd/server/encoding.py
httpetcd/tests/__init__.py
httpetcd/tests/functional/__init__.py
httpetcd/tests/functional/test_kv_ttl.py
httpetcd/tests/unit/__init__.py
httpetcd/tests/unit/library/__init__.py
httpetcd/tests/unit/library/test_session.py
httpetcd/tests/unit/raw/__init__.py
httpetcd/tests/unit/raw/entities/__init__.py
httpetcd/tests/unit/raw/entities/test_lease.py
httpetcd/tests/unit/raw/managers/__init__.py
httpetcd/tests/unit/raw/managers/test_kv.py
httpetcd/tests/unit/raw/managers/test_lease.py
httpetcd/tests/unit/wrapped/__init__.py
httpetcd/tests/unit/wrapped/entities/__init__.py
httpetcd/tests/unit/wrapped/entities/test_kvlock.py
httpetcd/tests/unit/wrapped/entities/test_lease.py
httpetcd/tests/unit/wrapped/managers/__init__.py
httpetcd/tests/unit/wrapped/managers/test_kvlock.py
httpetcd/wrapped/__init__.py
httpetcd/wrapped/client.py
httpetcd/wrapped/entities/__init__.py
httpetcd/wrapped/entities/kvlock.py
httpetcd/wrapped/entities/lease.py
httpetcd/wrapped/managers/__init__.py
httpetcd/wrapped/managers/kv.py
httpetcd/wrapped/managers/kvlock.py
httpetcd/wrapped/managers/lease.py
httpetcd-0.3.3.dist-info/licenses/AUTHORS
httpetcd-0.3.3.dist-info/licenses/LICENSE
httpetcd-0.3.3.dist-info/METADATA
httpetcd-0.3.3.dist-info/WHEEL
httpetcd-0.3.3.dist-info/pbr.json
httpetcd-0.3.3.dist-info/top_level.txt
httpetcd-0.3.3.dist-info/RECORD
